django_fcm_http_v1
