Metadata-Version: 2.1
Name: django-fcm-http
Version: 1.0.4
Summary: Django fcm http is a Django app to send push notifications to android, ios devices and web applications.
Home-page: https://github.com/Kazion500/django-fcm-http
Author: Patrick Kabwe
Author-email: patrickckabwe@gmail.com
License: MIT
Keywords: django,fcm,django-fcm-http,django-fcm,push,notification,http,rest,push notification,django fcm,django-fcm
Platform: UNKNOWN
Classifier: Environment :: Web Environment
Classifier: Framework :: Django
Classifier: Framework :: Django :: 3.0
Classifier: Intended Audience :: Developers
Classifier: License :: OSI Approved :: BSD License
Classifier: Operating System :: OS Independent
Classifier: Programming Language :: Python
Classifier: Programming Language :: Python :: 3
Classifier: Programming Language :: Python :: 3 :: Only
Classifier: Programming Language :: Python :: 3.8
Classifier: Programming Language :: Python :: 3.9
Classifier: Topic :: Internet :: WWW/HTTP
Classifier: Topic :: Internet :: WWW/HTTP :: Dynamic Content
Requires-Python: >=3.8
License-File: LICENSE
